LICENSE
MANIFEST.in
README.md
setup.py
src/ansible_autodoc_fork.egg-info/PKG-INFO
src/ansible_autodoc_fork.egg-info/SOURCES.txt
src/ansible_autodoc_fork.egg-info/dependency_links.txt
src/ansible_autodoc_fork.egg-info/requires.txt
src/ansible_autodoc_fork.egg-info/top_level.txt
src/ansibleautodoc/Annotation.py
src/ansibleautodoc/AutodocCli.py
src/ansibleautodoc/Config.py
src/ansibleautodoc/Contstants.py
src/ansibleautodoc/DocumentationGenerator.py
src/ansibleautodoc/DocumentationParser.py
src/ansibleautodoc/FileRegistry.py
src/ansibleautodoc/Utils.py
src/ansibleautodoc/__init__.py
src/ansibleautodoc/templates/cliprint/_action.j2
src/ansibleautodoc/templates/cliprint/_description.j2
src/ansibleautodoc/templates/cliprint/_tags.j2
src/ansibleautodoc/templates/cliprint/_todo.j2
src/ansibleautodoc/templates/cliprint/_var.j2
src/ansibleautodoc/templates/cliprint/print_to_cli.j2
src/ansibleautodoc/templates/doc_and_readme/README.md.j2
src/ansibleautodoc/templates/doc_and_readme/_example.j2
src/ansibleautodoc/templates/doc_and_readme/doc/_action.j2
src/ansibleautodoc/templates/doc_and_readme/doc/_tags.j2
src/ansibleautodoc/templates/doc_and_readme/doc/report.md.j2
src/ansibleautodoc/templates/doc_and_readme/doc/tags.md.j2
src/ansibleautodoc/templates/doc_and_readme/doc/todo.md.j2
src/ansibleautodoc/templates/doc_and_readme/doc/variables.md.j2
src/ansibleautodoc/templates/readme/README.md.j2
src/ansibleautodoc/templates/readme/_action.j2
src/ansibleautodoc/templates/readme/_dev_var_dump.txt.j2
src/ansibleautodoc/templates/readme/_example.j2
src/ansibleautodoc/templates/readme/_tags.j2
src/ansibleautodoc/templates/readme/_todo.j2
src/ansibleautodoc/templates/readme/_vars.j2
src/bin/ansible-autodoc-fork