Metadata-Version: 2.1
Name: ansible-autodoc-fork
Version: 0.5.6
Summary: FORK - Generate documentation from annotated playbooks and roles using templates
Home-page: https://github.com/rennym19/ansible-autodoc
Author: Andres Bott
Author-email: contact@andresbott.com
License: UNKNOWN
Platform: UNKNOWN
Classifier: Environment :: Console
Classifier: Intended Audience :: Developers
Classifier: Intended Audience :: Information Technology
Classifier: Intended Audience :: System Administrators
Classifier: License :: OSI Approved :: GNU Lesser General Public License v3 (LGPLv3)
Classifier: Natural Language :: English
Classifier: Operating System :: POSIX
Classifier: Programming Language :: Python :: 3 :: Only
Classifier: Topic :: System :: Installation/Setup
Classifier: Topic :: System :: Systems Administration
Classifier: Topic :: Utilities
Classifier: Topic :: Software Development
Classifier: Topic :: Software Development :: Documentation
